evil_pkg2/__init__.py
evil_pkg2-0.3.dist-info/METADATA
evil_pkg2-0.3.dist-info/WHEEL
evil_pkg2-0.3.dist-info/top_level.txt
evil_pkg2-0.3.dist-info/RECORD
