Metadata-Version: 2.2
Name: evil-pkg2
Version: 0.3
Summary: Just a harmless package :)
Dynamic: summary
